pyrankingfifa/__init__.py
pyrankingfifa/__main__.py
pyrankingfifa/exceptions.py
pyrankingfifa/parser.py
pyrankingfifa/team.py
pyrankingfifa/user_agents.py
pyrankingfifa/utils.py
pyrankingfifa-0.0.4.dist-info/LICENSE
pyrankingfifa-0.0.4.dist-info/METADATA
pyrankingfifa-0.0.4.dist-info/WHEEL
pyrankingfifa-0.0.4.dist-info/top_level.txt
pyrankingfifa-0.0.4.dist-info/RECORD
