Metadata-Version: 2.1
Name: pyrankingfifa
Version: 0.0.4
Summary: Python library to get FIFA Ranking since 2007.
Home-page: https://github.com/manucabral/pyrankingfifa
Author: Manuel Cabral
License: MIT License
Project-URL: Bug Tracker, https://github.com/manucabral/pyrankingfifa/issues
Project-URL: Documentation, https://github.com/manucabral/pyrankingfifa/readme.md
Keywords: fifa,ranking,soccer,football,worldcup,fifaranking
Requires-Python: >=3.9
License-File: LICENSE
